langchain_lean/__init__.py
langchain_lean/core.py
langchain_lean-0.0.1.dist-info/licenses/LICENSE
langchain_lean-0.0.1.dist-info/METADATA
langchain_lean-0.0.1.dist-info/WHEEL
langchain_lean-0.0.1.dist-info/top_level.txt
langchain_lean-0.0.1.dist-info/RECORD
