Metadata-Version: 2.4
Name: langchain_lean
Version: 0.0.1
Summary: A lean, lightweight version of LangChain.
Author-email: Your Name <you@example.com>
Project-URL: Homepage, https://github.com/your-username/langchain_lean
Project-URL: Bug Tracker, https://github.com/your-username/langchain_lean/issues
Classifier: Programming Language :: Python :: 3
Classifier: License :: OSI Approved :: MIT License
Classifier: Operating System :: OS Independent
Requires-Python: >=3.8
License-File: LICENSE
Dynamic: license-file
